[{"ScoutId": "Charlie", "MatchKey": "qm3", "Alliance": "blue", "DriverStation": 3, "TeamNumber": 4472, "StartingPosition": "Center", "ScoringSide": "Near/flush with HUB", "AutoNotes": "Shoot preloaded 8 balls  good accuracy but shoots rifht in front of hub and doesnt move", "TeleopNotes": "Shooting accuracy pretty decent seems to always have balls left in hopper so only shoots 5-10 in a cycle ", "ClimbSpeed": "", "EndgameNotes": "", "Disabled": false, "StabilityRating": "Moderately Tippy", "RobotStyleType": "Offensive", "DriverRating": "Average", "IntakeSpeed": "Average", "DefenseRating": "", "ShooterDefenseRating": "", "IntakeDefenseRating": "", "RatingNotes": "", "ThroughputSpeed": "Good", "TeleopClimb": None, "AutoClimb": false, "TeleopSingularCount": 0, "AutoSingularCount": 0, "AutoBatchCount": 0, "TeleopBatchCount": 0}, {"ScoutId": "Charlie", "MatchKey": "qm2", "Alliance": "blue", "DriverStation": 3, "TeamNumber": 8230, "StartingPosition": "Depot Side", "ScoringSide": "", "AutoNotes": "No auto", "TeleopNotes": "Intake jammed??? Tried pushing balls back and playing defense didn\x19t seem very effective\nDidn\x19t shoot at all", "ClimbSpeed": "", "EndgameNotes": "", "Disabled": false, "StabilityRating": "Stable", "RobotStyleType": "Defensive", "DriverRating": "Poor", "IntakeSpeed": "Very Slow", "DefenseRating": "Poor", "ShooterDefenseRating": "", "IntakeDefenseRating": "", "RatingNotes": "No offense whatsoever no passing no shooting intake and shooter both not working? Defense didn\x19t really do much tbh either", "ThroughputSpeed": "", "TeleopClimb": None, "AutoClimb": false, "TeleopSingularCount": 0, "AutoSingularCount": 0, "AutoBatchCount": 0, "TeleopBatchCount": 0}, {"ScoutId": "Charlie", "MatchKey": "qm1", "Alliance": "blue", "DriverStation": 3, "TeamNumber": 122, "StartingPosition": "Center", "ScoringSide": "", "AutoNotes": "No auto", "TeleopNotes": "Shooting arc bad missed everything far way too much power\n\nTried playing defense good movement over bump very fast but didn\x19t do anything offense wise no passing \n\nDefense pretty solid tbh so ", "ClimbSpeed": "", "EndgameNotes": "", "Disabled": false, "StabilityRating": "Stable", "RobotStyleType": "Defensive", "DriverRating": "Very Fluid", "IntakeSpeed": "", "DefenseRating": "Good", "ShooterDefenseRating": "", "IntakeDefenseRating": "", "RatingNotes": "No offense balls scored defense pretty ok ", "ThroughputSpeed": "", "TeleopClimb": None, "AutoClimb": false, "TeleopSingularCount": 0, "AutoSingularCount": 0, "AutoBatchCount": 0, "TeleopBatchCount": 0}, {"ScoutId": "Luke", "MatchKey": "qm2", "Alliance": "red", "DriverStation": 2, "TeamNumber": 3258, "StartingPosition": "Center", "ScoringSide": "Near/flush with HUB", "AutoNotes": "", "TeleopNotes": "", "ClimbSpeed": "", "EndgameNotes": "", "Disabled": false, "StabilityRating": "Moderately Tippy", "RobotStyleType": "Offensive", "DriverRating": "Poor", "IntakeSpeed": "Average", "DefenseRating": "Okay", "ShooterDefenseRating": "", "IntakeDefenseRating": "", "RatingNotes": "", "ThroughputSpeed": "Very Good", "TeleopClimb": None, "AutoClimb": false, "TeleopSingularCount": 0, "AutoSingularCount": 0, "AutoBatchCount": 0, "TeleopBatchCount": 0}, {"ScoutId": "nathan", "MatchKey": "qm1", "Alliance": "red", "DriverStation": 1, "TeamNumber": 2186, "StartingPosition": "Depot Side", "ScoringSide": "", "AutoNotes": "no auto", "TeleopNotes": "", "ClimbSpeed": "", "EndgameNotes": "", "Disabled": false, "StabilityRating": "Stable", "RobotStyleType": "Offensive", "DriverRating": "Average", "IntakeSpeed": "", "DefenseRating": "", "ShooterDefenseRating": "", "IntakeDefenseRating": "", "RatingNotes": "", "ThroughputSpeed": "", "TeleopClimb": None, "AutoClimb": false, "TeleopSingularCount": 0, "AutoSingularCount": 0, "AutoBatchCount": 0, "TeleopBatchCount": 0}, {"ScoutId": "Jai", "MatchKey": "qm1", "Alliance": "blue", "DriverStation": 2, "TeamNumber": 6882, "StartingPosition": "Depot Side", "ScoringSide": "", "AutoNotes": "", "TeleopNotes": "", "ClimbSpeed": "", "EndgameNotes": "", "Disabled": false, "StabilityRating": "Stable", "RobotStyleType": "Offensive", "DriverRating": "Very Poor", "IntakeSpeed": "Slow", "DefenseRating": "", "ShooterDefenseRating": "Okay", "IntakeDefenseRating": "Okay", "RatingNotes": "", "ThroughputSpeed": "Poor", "TeleopClimb": None, "AutoClimb": false, "TeleopSingularCount": 0, "AutoSingularCount": 0, "AutoBatchCount": 0, "TeleopBatchCount": 0}, {"ScoutId": "Jai", "MatchKey": "qm2", "Alliance": "blue", "DriverStation": 2, "TeamNumber": 8326, "StartingPosition": "Center", "ScoringSide": "", "AutoNotes": "", "TeleopNotes": "", "ClimbSpeed": "", "EndgameNotes": "", "Disabled": false, "StabilityRating": "Stable", "RobotStyleType": "Defensive", "DriverRating": "Average", "IntakeSpeed": "", "DefenseRating": "", "ShooterDefenseRating": "", "IntakeDefenseRating": "", "RatingNotes": "", "ThroughputSpeed": "", "TeleopClimb": None, "AutoClimb": false, "TeleopSingularCount": 0, "AutoSingularCount": 0, "AutoBatchCount": 0, "TeleopBatchCount": 0}, {"ScoutId": "Jai", "MatchKey": "qm3", "Alliance": "blue", "DriverStation": 2, "TeamNumber": 116, "StartingPosition": "Depot Side", "ScoringSide": "", "AutoNotes": "", "TeleopNotes": "", "ClimbSpeed": "", "EndgameNotes": "", "Disabled": false, "StabilityRating": "Stable", "RobotStyleType": "Defensive", "DriverRating": "Very Poor", "IntakeSpeed": "", "DefenseRating": "", "ShooterDefenseRating": "", "IntakeDefenseRating": "", "RatingNotes": "They did not play", "ThroughputSpeed": "", "TeleopClimb": None, "AutoClimb": false, "TeleopSingularCount": 0, "AutoSingularCount": 0, "AutoBatchCount": 0, "TeleopBatchCount": 0}, {"ScoutId": "Ryan Li ", "MatchKey": "qm2", "Alliance": "blue", "DriverStation": 1, "TeamNumber": 2028, "StartingPosition": "Center", "ScoringSide": "Near/flush with HUB", "AutoNotes": "", "TeleopNotes": "Missed a lot of fuel (high thru put but low accuracy)", "ClimbSpeed": "", "EndgameNotes": "", "Disabled": false, "StabilityRating": "Moderately Tippy", "RobotStyleType": "Offensive", "DriverRating": "Fluid", "IntakeSpeed": "Average", "DefenseRating": "", "ShooterDefenseRating": "", "IntakeDefenseRating": "", "RatingNotes": "", "ThroughputSpeed": "Very Good", "TeleopClimb": None, "AutoClimb": false, "TeleopSingularCount": 0, "AutoSingularCount": 0, "AutoBatchCount": 0, "TeleopBatchCount": 0}, {"ScoutId": "Ryan Li ", "MatchKey": "qm3", "Alliance": "blue", "DriverStation": 1, "TeamNumber": 526, "StartingPosition": "Human-Player Side", "ScoringSide": "", "AutoNotes": "", "TeleopNotes": "Intake broke did a lot of pushing balls", "ClimbSpeed": "", "EndgameNotes": "", "Disabled": false, "StabilityRating": "Moderately Tippy", "RobotStyleType": "Offensive", "DriverRating": "Average", "IntakeSpeed": "", "DefenseRating": "", "ShooterDefenseRating": "", "IntakeDefenseRating": "", "RatingNotes": "Hopper popped out as well ", "ThroughputSpeed": "Okay", "TeleopClimb": None, "AutoClimb": false, "TeleopSingularCount": 0, "AutoSingularCount": 0, "AutoBatchCount": 0, "TeleopBatchCount": 0}]